Workbook
Name Aporte: 'GB Invest'!$D$17
Name patrimonio: 'GB Invest'!$D$20
Name qtd_anos: 'GB Invest'!$D$18
Name Rendimento_Carteira: 'GB Invest'!$D$13
Name Salario: 'GB Invest'!$D$12
Name sugestao_investimento: 'GB Invest'!$D$14
Name tx_mensal: 'GB Invest'!$D$19

Sheet GB Invest
B11: CONFIGURAÇÕES
B12: Salário | D12: 5000
B13: Rendimento Carteira | D13: 0.0089
B14: Sugestão de Investimento (30%) | D14: =Salario*30% -> 1500
B16: INVESTIMENTO MENSAL
B17: Quanto Investir por Mês? | D17: 1500
B18: Por quantos anos? | D18: 1
B19: Taxa de rendimento mensal? | D19: 0.01079
B20: Patrimônio Acumulado? | D20: =FV(tx_mensal,qtd_anos*12,Aporte*-1) -> 19107.579
B21: Dividendos Mensais? | D21: =patrimonio*Rendimento_Carteira -> 170.05745
B23: CENÁRIOS | D23: Dividendo
A24: 2 | B24: Quanto em 2 Anos? | C24: =FV(tx_mensal,$A24*12,Aporte*-1) -> 40841.441 | D24: =C24*Rendimento_Carteira -> 363.48882
A25: 5 | B25: Quanto em 5 Anos? | C25: =FV(tx_mensal,$A25*12,Aporte*-1) -> 125665.37 | D25: =C25*Rendimento_Carteira -> 1118.4218
A26: 10 | B26: Quanto em 10 Anos? | C26: =FV(tx_mensal,$A26*12,Aporte*-1) -> 364926.32 | D26: =C26*Rendimento_Carteira -> 3247.8442
A27: 20 | B27: Quanto em 20 Anos? | C27: =FV(tx_mensal,$A27*12,Aporte*-1) -> 1687797.6 | D27: =C27*Rendimento_Carteira -> 15021.399
A28: 30 | B28: Quanto em 30 Anos? | C28: =FV(tx_mensal,$A28*12,Aporte*-1) -> 6483254.5 | D28: =C28*Rendimento_Carteira -> 57700.965
B31: PERFIL | C31: Conservador | D31: =VLOOKUP('GB Invest'!$C$31,Tbl_Chaves!$A$24:$B$26,2,) -> Foco em segurança e renda fixa; rejeita riscos em troca de estabilidade.
B32: Valor a ser Investido por Mês | C32: =Aporte -> 1500
B34: Tipo de FII | C34: Percentual Sugerido | D34: Valores
B35: PAPEL | C35: =VLOOKUP($C$31&"-"&B35,Tbl_Chaves!$A:$D,4,FALSE) -> 0.3 | D35: =$C35*Aporte -> 450
B36: TIJOLO | C36: =VLOOKUP($C$31&"-"&B36,Tbl_Chaves!$A:$D,4,FALSE) -> 0.5 | D36: =$C36*Aporte -> 750
B37: HÍBRIDOS | C37: =VLOOKUP($C$31&"-"&B37,Tbl_Chaves!$A:$D,4,FALSE) -> 0.1 | D37: =$C37*Aporte -> 150
B38: FOFs | C38: =VLOOKUP($C$31&"-"&B38,Tbl_Chaves!$A:$D,4,FALSE) -> 0.1 | D38: =$C38*Aporte -> 150
B39: DESENVOLVIMENTO | C39: =VLOOKUP($C$31&"-"&B39,Tbl_Chaves!$A:$D,4,FALSE) -> 0 | D39: =$C39*Aporte -> 0
B40: HOTELARIAS | C40: =VLOOKUP($C$31&"-"&B40,Tbl_Chaves!$A:$D,4,FALSE) -> 0 | D40: =$C40*Aporte -> 0
D41: =SUM(D35:D40) -> 1500

Sheet Tbl_Chaves
A2: CHAVE | B2: PERFIL | C2: TIPO DE FII | D2: %
A3: =B3&"-"&C3 -> Conservador-PAPEL | B3: Conservador | C3: PAPEL | D3: 0.3
A4: =B4&"-"&C4 -> Conservador-TIJOLO | B4: Conservador | C4: TIJOLO | D4: 0.5
A5: =B5&"-"&C5 -> Conservador-HÍBRIDOS | B5: Conservador | C5: HÍBRIDOS | D5: 0.1
A6: =B6&"-"&C6 -> Conservador-FOFs | B6: Conservador | C6: FOFs | D6: 0.1
A7: =B7&"-"&C7 -> Conservador-DESENVOLVIMENTO | B7: Conservador | C7: DESENVOLVIMENTO | D7: 0
A8: =B8&"-"&C8 -> Conservador-HOTELARIAS | B8: Conservador | C8: HOTELARIAS | D8: 0
A9: =B9&"-"&C9 -> Moderado-PAPEL | B9: Moderado | C9: PAPEL | D9: 0.32
A10: =B10&"-"&C10 -> Moderado-TIJOLO | B10: Moderado | C10: TIJOLO | D10: 0.35
A11: =B11&"-"&C11 -> Moderado-HÍBRIDOS | B11: Moderado | C11: HÍBRIDOS | D11: 0.08
A12: =B12&"-"&C12 -> Moderado-FOFs | B12: Moderado | C12: FOFs | D12: 0.05
A13: =B13&"-"&C13 -> Moderado-DESENVOLVIMENTO | B13: Moderado | C13: DESENVOLVIMENTO | D13: 0.1
A14: =B14&"-"&C14 -> Moderado-HOTELARIAS | B14: Moderado | C14: HOTELARIAS | D14: 0.1
... A20: =B20&"-"&C20 -> Agressivo-HOTELARIAS | B20: Agressivo | C20: HOTELARIAS | D20: 0.1
A23: Perfil | B23: Explicação Resumida
A24: Conservador | B24: Foco em segurança e renda fixa; rejeita riscos em troca de estabilidade.
A25: Moderado | B25: Equilíbrio entre segurança e risco; usa renda variável moderada para superar a inflação.
A26: Agressivo | B26: Foco em máxima rentabilidade; tolera alta volatilidade e riscos por ganhos maiores.
